{"docs":{"name":"Foreman","info":"\n\u003cp\u003eForeman API v1 is deprecated. Please use v2. If you still need to use v1, you may do so by either passing ‘version=1’ in the Accept Header or using api/v1/ in the URL.\u003c/p\u003e\n","copyright":"","doc_url":"../../../apidoc/v1","api_url":"/api","resources":[{"doc_url":"../../../apidoc/v1/ptables","api_url":"/api","name":"Ptables","short_description":null,"full_description":null,"version":"v1","formats":null,"metadata":null,"methods":[{"doc_url":"../../../apidoc/v1/ptables/index","name":"index","apis":[{"api_url":"/api/ptables","http_method":"GET","short_description":"List all ptables.","deprecated":null}],"formats":null,"full_description":"","errors":[],"params":[{"name":"search","full_name":"search","description":"\n\u003cp\u003efilter results\u003c/p\u003e\n","required":false,"allow_nil":false,"validator":"Must be String","expected_type":"string","metadata":null,"show":true,"validations":[]},{"name":"order","full_name":"order","description":"\n\u003cp\u003esort results\u003c/p\u003e\n","required":false,"allow_nil":false,"validator":"Must be String","expected_type":"string","metadata":null,"show":true,"validations":[]},{"name":"page","full_name":"page","description":"\n\u003cp\u003epaginate results\u003c/p\u003e\n","required":false,"allow_nil":false,"validator":"Must be String","expected_type":"string","metadata":null,"show":true,"validations":[]},{"name":"per_page","full_name":"per_page","description":"\n\u003cp\u003enumber of entries per request\u003c/p\u003e\n","required":false,"allow_nil":false,"validator":"Must be String","expected_type":"string","metadata":null,"show":true,"validations":[]}],"examples":["GET /api/ptables\n200\n[\n  {\n    \"template\": {\n      \"name\": \"ptable21\",\n      \"id\": 1007981702,\n      \"layout\": \"zerombr\\\\nclearpart --all    --initlabel\\\\npart /boot --fstype ext3 --size=\u003c%= 10 * 10 %\u003e --asprimary\\\\npart /     --f   stype ext3 --size=1024 --grow\\\\npart swap  --recommended\",\n      \"os_family\": \"Redhat\",\n      \"created_at\": \"2016-03-10 15:51:35 UTC\",\n      \"updated_at\": \"2016-03-10 15:51:35 UTC\"\n    }\n  }\n]"],"metadata":null,"see":[],"headers":[],"show":true}],"headers":null}],"link_extension":".gl.html"}}