{"docs":{"name":"Foreman","info":"\n\u003cp\u003eForeman API v2 is currently the default API version.\u003c/p\u003e\n","copyright":"","doc_url":"../../../apidoc/v2","api_url":"/api","resources":[{"doc_url":"../../../apidoc/v2/subnets","api_url":"/api","name":"Subnets","short_description":null,"full_description":null,"version":"v2","formats":null,"metadata":null,"methods":[{"doc_url":"../../../apidoc/v2/subnets/destroy","name":"destroy","apis":[{"api_url":"/api/subnets/:id","http_method":"DELETE","short_description":"Apagar uma subrede","deprecated":null}],"formats":null,"full_description":"","errors":[],"params":[{"name":"id","full_name":"id","description":"\n\u003cp\u003eIdentificador numérico da sub-rede\u003c/p\u003e\n","required":true,"allow_nil":false,"validator":"Must be a number.","expected_type":"string","metadata":null,"show":true,"validations":[]}],"examples":["DELETE /api/subnets/281110143-four\n200\n{\n  \"id\": 281110143,\n  \"network\": \"3.3.5.0\",\n  \"mask\": \"255.255.255.0\",\n  \"priority\": null,\n  \"name\": \"four\",\n  \"vlanid\": \"44\",\n  \"created_at\": \"2016-03-10T15:51:23.000Z\",\n  \"updated_at\": \"2016-03-10T15:51:23.000Z\",\n  \"dhcp_id\": null,\n  \"tftp_id\": 298486374,\n  \"gateway\": null,\n  \"dns_primary\": null,\n  \"dns_secondary\": null,\n  \"from\": null,\n  \"to\": null,\n  \"dns_id\": null,\n  \"ipam\": \"DHCP\",\n  \"boot_mode\": \"DHCP\",\n  \"to_label\": \"four (3.3.5.0/24)\"\n}"],"metadata":null,"see":[],"headers":[],"show":true}],"headers":null}],"link_extension":".pt_BR.html"}}