{"docs":{"name":"Foreman","info":"\n<p>Foreman v2 is stable and recommended for use. You may use v2 by either passing \u2018version=2\u2019 in the Accept Header or using api/v2/ in the URL.</p>\n","copyright":"","doc_url":"../../../apidoc/v2","api_url":"/api","resources":[{"doc_url":"../../../apidoc/v2/locations","api_url":"/api","name":"Locations","short_description":null,"full_description":null,"version":"v2","formats":null,"metadata":null,"methods":[{"doc_url":"../../../apidoc/v2/locations/create","name":"create","apis":[{"api_url":"/api/locations","http_method":"POST","short_description":"Create a location","deprecated":null}],"formats":null,"full_description":"","errors":[],"params":[{"name":"location","full_name":"location","description":"","required":true,"allow_nil":false,"validator":"Must be a Hash","expected_type":"hash","metadata":null,"show":true,"params":[{"name":"name","full_name":"location[name]","description":"","required":true,"allow_nil":false,"validator":"Must be String","expected_type":"string","metadata":null,"show":true},{"name":"user_ids","full_name":"location[user_ids]","description":"\n<p>User IDs</p>\n","required":false,"allow_nil":true,"validator":"Must be an array of any type","expected_type":"array","metadata":null,"show":true},{"name":"smart_proxy_ids","full_name":"location[smart_proxy_ids]","description":"\n<p>Smart proxy IDs</p>\n","required":false,"allow_nil":true,"validator":"Must be an array of any type","expected_type":"array","metadata":null,"show":true},{"name":"compute_resource_ids","full_name":"location[compute_resource_ids]","description":"\n<p>Compute resource IDs</p>\n","required":false,"allow_nil":true,"validator":"Must be an array of any type","expected_type":"array","metadata":null,"show":true},{"name":"media_ids","full_name":"location[media_ids]","description":"\n<p>Media IDs</p>\n","required":false,"allow_nil":true,"validator":"Must be an array of any type","expected_type":"array","metadata":null,"show":true},{"name":"config_template_ids","full_name":"location[config_template_ids]","description":"\n<p>Provisioning template IDs</p>\n","required":false,"allow_nil":true,"validator":"Must be an array of any type","expected_type":"array","metadata":null,"show":true},{"name":"domain_ids","full_name":"location[domain_ids]","description":"\n<p>Domain IDs</p>\n","required":false,"allow_nil":true,"validator":"Must be an array of any type","expected_type":"array","metadata":null,"show":true},{"name":"realm_ids","full_name":"location[realm_ids]","description":"\n<p>Realm IDs</p>\n","required":false,"allow_nil":true,"validator":"Must be an array of any type","expected_type":"array","metadata":null,"show":true},{"name":"hostgroup_ids","full_name":"location[hostgroup_ids]","description":"\n<p>Host group IDs</p>\n","required":false,"allow_nil":true,"validator":"Must be an array of any type","expected_type":"array","metadata":null,"show":true},{"name":"environment_ids","full_name":"location[environment_ids]","description":"\n<p>Environment IDs</p>\n","required":false,"allow_nil":true,"validator":"Must be an array of any type","expected_type":"array","metadata":null,"show":true},{"name":"subnet_ids","full_name":"location[subnet_ids]","description":"\n<p>Subnet IDs</p>\n","required":false,"allow_nil":true,"validator":"Must be an array of any type","expected_type":"array","metadata":null,"show":true}]}],"examples":[],"metadata":null,"see":[]}]}],"link_extension":".html"}}