{"docs":{"name":"Foreman","info":"\n\u003Cp\u003EForeman API v2 is currently the default API version.\u003C/p\u003E\n","copyright":"","doc_url":"../../../apidoc/v2","api_url":"/api","resources":[{"doc_url":"../../../apidoc/v2/deployments","api_url":"/api","name":"Deployments","short_description":null,"full_description":null,"version":"v2","formats":null,"metadata":null,"methods":[{"doc_url":"../../../apidoc/v2/deployments/create","name":"create","apis":[{"api_url":"/api/deployments","http_method":"POST","short_description":"Create a deployment","deprecated":null}],"formats":null,"full_description":"","errors":[],"params":[{"name":"deployment","full_name":"deployment","description":"","required":true,"allow_nil":false,"validator":"Must be a Hash","expected_type":"hash","metadata":null,"show":true,"params":[{"name":"name","full_name":"deployment[name]","description":"\n\u003Cp\u003EName for the deployment\u003C/p\u003E\n","required":true,"allow_nil":false,"validator":"Must be String","expected_type":"string","metadata":null,"show":true},{"name":"stack_id","full_name":"deployment[stack_id]","description":"\n\u003Cp\u003EId of the stack to deploy\u003C/p\u003E\n","required":true,"allow_nil":false,"validator":"Must be an identifier, string from 1 to 128 characters containing only alphanumeric characters, space, underscore(_), hypen(-) with no leading or trailing space.","expected_type":"string","metadata":null,"show":true}]}],"examples":[],"metadata":null,"see":[]}]}],"link_extension":".html"}}