{"docs":{"name":"Foreman","info":"\n\u003cp\u003eForeman API v1 is deprecated. Please use v2. If you still need to use v1, you may do so by either passing ‘version=1’ in the Accept Header or using api/v1/ in the URL.\u003c/p\u003e\n","copyright":"","doc_url":"../../apidoc/v1","api_url":"/api","resources":[{"doc_url":"../../apidoc/v1/models","api_url":"/api","name":"Models","short_description":null,"full_description":null,"version":"v1","formats":null,"metadata":null,"methods":[{"doc_url":"../../apidoc/v1/models/index","name":"index","apis":[{"api_url":"/api/models","http_method":"GET","short_description":"List all models.","deprecated":null}],"formats":null,"full_description":"","errors":[],"params":[{"name":"search","full_name":"search","description":"\n\u003cp\u003e过滤结果\u003c/p\u003e\n","required":false,"allow_nil":false,"validator":"Must be String","expected_type":"string","metadata":null,"show":true,"validations":[]},{"name":"order","full_name":"order","description":"\n\u003cp\u003e结果排序\u003c/p\u003e\n","required":false,"allow_nil":false,"validator":"Must be String","expected_type":"string","metadata":null,"show":true,"validations":[]},{"name":"page","full_name":"page","description":"\n\u003cp\u003e页数\u003c/p\u003e\n","required":false,"allow_nil":false,"validator":"Must be String","expected_type":"string","metadata":null,"show":true,"validations":[]},{"name":"per_page","full_name":"per_page","description":"\n\u003cp\u003e每个请求中的条目数\u003c/p\u003e\n","required":false,"allow_nil":false,"validator":"Must be String","expected_type":"string","metadata":null,"show":true,"validations":[]}],"examples":["GET /api/models\n200\n[\n  {\n    \"model\": {\n      \"id\": 980190962,\n      \"name\": \"KVM\",\n      \"info\": \"Virtual Machine\",\n      \"created_at\": \"2016-03-10 15:51:22 UTC\",\n      \"updated_at\": \"2016-03-10 15:51:22 UTC\",\n      \"vendor_class\": null,\n      \"hardware_model\": null\n    }\n  },\n  {\n    \"model\": {\n      \"id\": 139037058,\n      \"name\": \"SUN V210\",\n      \"info\": null,\n      \"created_at\": \"2016-03-10 15:51:22 UTC\",\n      \"updated_at\": \"2016-03-10 15:51:22 UTC\",\n      \"vendor_class\": \"Sun-Fire-V210\",\n      \"hardware_model\": \"SUN4U\"\n    }\n  }\n]"],"metadata":null,"see":[],"headers":[],"show":true},{"doc_url":"../../apidoc/v1/models/show","name":"show","apis":[{"api_url":"/api/models/:id","http_method":"GET","short_description":"Show a model.","deprecated":null}],"formats":null,"full_description":"","errors":[],"params":[{"name":"id","full_name":"id","description":"","required":true,"allow_nil":false,"validator":"Must be an identifier, string from 1 to 128 characters containing only alphanumeric characters, space, underscore(_), hypen(-) with no leading or trailing space.","expected_type":"string","metadata":null,"show":true,"validations":[]}],"examples":["GET /api/models/KVM\n200\n{\n  \"model\": {\n    \"id\": 980190962,\n    \"name\": \"KVM\",\n    \"info\": \"Virtual Machine\",\n    \"created_at\": \"2016-03-10 15:51:22 UTC\",\n    \"updated_at\": \"2016-03-10 15:51:22 UTC\",\n    \"vendor_class\": null,\n    \"hardware_model\": null\n  }\n}"],"metadata":null,"see":[],"headers":[],"show":true},{"doc_url":"../../apidoc/v1/models/create","name":"create","apis":[{"api_url":"/api/models","http_method":"POST","short_description":"Create a model.","deprecated":null}],"formats":null,"full_description":"","errors":[],"params":[{"name":"model","full_name":"model","description":"","required":true,"allow_nil":false,"validator":"Must be a Hash","expected_type":"hash","metadata":null,"show":true,"validations":[],"params":[{"name":"name","full_name":"model[name]","description":"","required":true,"allow_nil":false,"validator":"Must be String","expected_type":"string","metadata":null,"show":true,"validations":[]},{"name":"info","full_name":"model[info]","description":"","required":false,"allow_nil":false,"validator":"Must be String","expected_type":"string","metadata":null,"show":true,"validations":[]},{"name":"vendor_class","full_name":"model[vendor_class]","description":"","required":false,"allow_nil":false,"validator":"Must be String","expected_type":"string","metadata":null,"show":true,"validations":[]},{"name":"hardware_model","full_name":"model[hardware_model]","description":"","required":false,"allow_nil":false,"validator":"Must be String","expected_type":"string","metadata":null,"show":true,"validations":[]}]}],"examples":["POST /api/models\n{\n  \"model\": {\n    \"name\": \"new model\"\n  }\n}\n201\n{\n  \"model\": {\n    \"id\": 980190963,\n    \"name\": \"new model\",\n    \"info\": null,\n    \"created_at\": \"2016-03-10T15:51:35.006Z\",\n    \"updated_at\": \"2016-03-10T15:51:35.006Z\",\n    \"vendor_class\": null,\n    \"hardware_model\": null,\n    \"hosts_count\": 0\n  }\n}"],"metadata":null,"see":[],"headers":[],"show":true},{"doc_url":"../../apidoc/v1/models/update","name":"update","apis":[{"api_url":"/api/models/:id","http_method":"PUT","short_description":"Update a model.","deprecated":null}],"formats":null,"full_description":"","errors":[],"params":[{"name":"id","full_name":"id","description":"","required":true,"allow_nil":false,"validator":"Must be String","expected_type":"string","metadata":null,"show":true,"validations":[]},{"name":"model","full_name":"model","description":"","required":true,"allow_nil":false,"validator":"Must be a Hash","expected_type":"hash","metadata":null,"show":true,"validations":[],"params":[{"name":"name","full_name":"model[name]","description":"","required":false,"allow_nil":false,"validator":"Must be String","expected_type":"string","metadata":null,"show":true,"validations":[]},{"name":"info","full_name":"model[info]","description":"","required":false,"allow_nil":false,"validator":"Must be String","expected_type":"string","metadata":null,"show":true,"validations":[]},{"name":"vendor_class","full_name":"model[vendor_class]","description":"","required":false,"allow_nil":false,"validator":"Must be String","expected_type":"string","metadata":null,"show":true,"validations":[]},{"name":"hardware_model","full_name":"model[hardware_model]","description":"","required":false,"allow_nil":false,"validator":"Must be String","expected_type":"string","metadata":null,"show":true,"validations":[]}]}],"examples":["PUT /api/models/KVM\n{\n  \"name\": \"KVM\",\n  \"model\": {\n    \"name\": \"KVM\"\n  }\n}\n200\n{\n  \"model\": {\n    \"id\": 980190962,\n    \"name\": \"KVM\",\n    \"info\": \"Virtual Machine\",\n    \"created_at\": \"2016-03-10T15:51:22.000Z\",\n    \"updated_at\": \"2016-03-10T15:51:22.000Z\",\n    \"vendor_class\": null,\n    \"hardware_model\": null,\n    \"hosts_count\": 0\n  }\n}"],"metadata":null,"see":[],"headers":[],"show":true},{"doc_url":"../../apidoc/v1/models/destroy","name":"destroy","apis":[{"api_url":"/api/models/:id","http_method":"DELETE","short_description":"Delete a model.","deprecated":null}],"formats":null,"full_description":"","errors":[],"params":[{"name":"id","full_name":"id","description":"","required":true,"allow_nil":false,"validator":"Must be String","expected_type":"string","metadata":null,"show":true,"validations":[]}],"examples":["DELETE /api/models/KVM\n200\n{\n  \"model\": {\n    \"id\": 980190962,\n    \"name\": \"KVM\",\n    \"info\": \"Virtual Machine\",\n    \"created_at\": \"2016-03-10T15:51:22.000Z\",\n    \"updated_at\": \"2016-03-10T15:51:22.000Z\",\n    \"vendor_class\": null,\n    \"hardware_model\": null,\n    \"hosts_count\": 0\n  }\n}"],"metadata":null,"see":[],"headers":[],"show":true}],"headers":null}],"link_extension":".zh_CN.html"}}