{"docs":{"name":"Foreman","info":"\n<p>Foreman v2 is stable and recommended for use. You may use v2 by either passing \u2018version=2\u2019 in the Accept Header or using api/v2/ in the URL.</p>\n","copyright":"","doc_url":"../../apidoc/v2","api_url":"/api","resources":[{"doc_url":"../../apidoc/v2/environments","api_url":"/api","name":"Environments","short_description":null,"full_description":null,"version":"v2","formats":null,"metadata":null,"methods":[{"doc_url":"../../apidoc/v2/environments/import_puppetclasses","name":"import_puppetclasses","apis":[{"api_url":"/api/smart_proxies/:id/import_puppetclasses","http_method":"POST","short_description":"Import puppet classes from puppet proxy.","deprecated":null},{"api_url":"/api/smart_proxies/:smart_proxy_id/environments/:id/import_puppetclasses","http_method":"POST","short_description":"Import puppet classes from puppet proxy for an environment","deprecated":null},{"api_url":"/api/environments/:environment_id/smart_proxies/:id/import_puppetclasses","http_method":"POST","short_description":"Import puppet classes from puppet proxy for an environment","deprecated":null}],"formats":null,"full_description":"","errors":[],"params":[{"name":"id","full_name":"id","description":"","required":true,"allow_nil":false,"validator":"Must be an identifier, string from 1 to 128 characters containing only alphanumeric characters, space, underscore(_), hypen(-) with no leading or trailing space.","expected_type":"string","metadata":null,"show":true},{"name":"smart_proxy_id","full_name":"smart_proxy_id","description":"","required":false,"allow_nil":false,"validator":"Must be String","expected_type":"string","metadata":null,"show":true},{"name":"environment_id","full_name":"environment_id","description":"","required":false,"allow_nil":false,"validator":"Must be String","expected_type":"string","metadata":null,"show":true},{"name":"dryrun","full_name":"dryrun","description":"","required":false,"allow_nil":false,"validator":"Must be 'true' or 'false'","expected_type":"string","metadata":null,"show":true},{"name":"except","full_name":"except","description":"\n<p>Optional comma-delimited string containing either \u2018new\u2019, \u2018updated\u2019, or \u2018obsolete\u2019 that is used to limit the imported Puppet classes</p>\n","required":false,"allow_nil":false,"validator":"Must be String","expected_type":"string","metadata":null,"show":true}],"examples":[],"metadata":null,"see":[]},{"doc_url":"../../apidoc/v2/environments/index","name":"index","apis":[{"api_url":"/api/environments","http_method":"GET","short_description":"List all environments","deprecated":null}],"formats":null,"full_description":"","errors":[],"params":[{"name":"search","full_name":"search","description":"\n<p>filter results</p>\n","required":false,"allow_nil":false,"validator":"Must be String","expected_type":"string","metadata":null,"show":true},{"name":"order","full_name":"order","description":"\n<p>sort results</p>\n","required":false,"allow_nil":false,"validator":"Must be String","expected_type":"string","metadata":null,"show":true},{"name":"page","full_name":"page","description":"\n<p>paginate results</p>\n","required":false,"allow_nil":false,"validator":"Must be String","expected_type":"string","metadata":null,"show":true},{"name":"per_page","full_name":"per_page","description":"\n<p>number of entries per request</p>\n","required":false,"allow_nil":false,"validator":"Must be String","expected_type":"string","metadata":null,"show":true}],"examples":["GET /api/environments\n200\n{\n  \"total\": 3,\n  \"subtotal\": 3,\n  \"page\": 1,\n  \"per_page\": 20,\n  \"search\": null,\n  \"sort\": {\n    \"by\": null,\n    \"order\": null\n  },\n  \"results\": [\n    {\n      \"name\": \"global_puppetmaster\",\n      \"id\": 153855663,\n      \"created_at\": \"2014-09-02T14:00:17Z\",\n      \"updated_at\": \"2014-09-02T14:00:17Z\"\n    },\n    {\n      \"name\": \"production\",\n      \"id\": 334344675,\n      \"created_at\": \"2014-09-02T14:00:17Z\",\n      \"updated_at\": \"2014-09-02T14:00:17Z\"\n    },\n    {\n      \"name\": \"testing\",\n      \"id\": 687036937,\n      \"created_at\": \"2014-09-02T14:00:17Z\",\n      \"updated_at\": \"2014-09-02T14:00:17Z\"\n    }\n  ]\n}"],"metadata":null,"see":[]},{"doc_url":"../../apidoc/v2/environments/show","name":"show","apis":[{"api_url":"/api/environments/:id","http_method":"GET","short_description":"Show an environment","deprecated":null}],"formats":null,"full_description":"","errors":[],"params":[{"name":"id","full_name":"id","description":"","required":true,"allow_nil":false,"validator":"Must be an identifier, string from 1 to 128 characters containing only alphanumeric characters, space, underscore(_), hypen(-) with no leading or trailing space.","expected_type":"string","metadata":null,"show":true}],"examples":["GET /api/environments/production\n200\n{\n  \"name\": \"production\",\n  \"id\": 334344675,\n  \"created_at\": \"2014-09-02T14:00:17Z\",\n  \"updated_at\": \"2014-09-02T14:00:17Z\",\n  \"locations\": [\n    {\n      \"id\": 255093256,\n      \"name\": \"Location 1\",\n      \"title\": \"Location 1\"\n    }\n  ],\n  \"organizations\": [\n    {\n      \"id\": 447626438,\n      \"name\": \"Organization 1\",\n      \"title\": \"Organization 1\"\n    }\n  ],\n  \"template_combinations\": [\n    {\n      \"id\": 980190962,\n      \"config_template_id\": 943779058,\n      \"config_template_name\": \"MyString\",\n      \"hostgroup_id\": 636252244,\n      \"hostgroup_name\": \"Common\",\n      \"environment_id\": 334344675,\n      \"environment_name\": \"production\"\n    },\n    {\n      \"id\": 113629430,\n      \"config_template_id\": 104314179,\n      \"config_template_name\": \"MyFinish\",\n      \"hostgroup_id\": null,\n      \"hostgroup_name\": null,\n      \"environment_id\": 334344675,\n      \"environment_name\": \"production\"\n    },\n    {\n      \"id\": 281110143,\n      \"config_template_id\": 269958254,\n      \"config_template_name\": \"MyString2\",\n      \"hostgroup_id\": 636252244,\n      \"hostgroup_name\": \"Common\",\n      \"environment_id\": 334344675,\n      \"environment_name\": \"production\"\n    }\n  ],\n  \"puppetclasses\": [\n    {\n      \"id\": 298486374,\n      \"name\": \"apache\",\n      \"module_name\": \"apache\"\n    },\n    {\n      \"id\": 638205575,\n      \"name\": \"auth\",\n      \"module_name\": \"auth\"\n    },\n    {\n      \"id\": 980190962,\n      \"name\": \"base\",\n      \"module_name\": \"base\"\n    },\n    {\n      \"id\": 51848956,\n      \"name\": \"chkmk\",\n      \"module_name\": \"chkmk\"\n    },\n    {\n      \"id\": 1018350795,\n      \"name\": \"nagios\",\n      \"module_name\": \"nagios\"\n    },\n    {\n      \"id\": 374648174,\n      \"name\": \"pam\",\n      \"module_name\": \"pam\"\n    },\n    {\n      \"id\": 281110143,\n      \"name\": \"vim\",\n      \"module_name\": \"vim\"\n    }\n  ]\n}"],"metadata":null,"see":[]},{"doc_url":"../../apidoc/v2/environments/create","name":"create","apis":[{"api_url":"/api/environments","http_method":"POST","short_description":"Create an environment","deprecated":null}],"formats":null,"full_description":"","errors":[],"params":[{"name":"environment","full_name":"environment","description":"","required":true,"allow_nil":false,"validator":"Must be a Hash","expected_type":"hash","metadata":null,"show":true,"params":[{"name":"name","full_name":"environment[name]","description":"","required":true,"allow_nil":false,"validator":"Must be String","expected_type":"string","metadata":null,"show":true}]}],"examples":["POST /api/environments\n{\n  \"environment\": {\n    \"name\": \"Development\"\n  }\n}\n200\n{\n  \"name\": \"Development\",\n  \"id\": 687036971,\n  \"created_at\": \"2014-09-02T14:00:39Z\",\n  \"updated_at\": \"2014-09-02T14:00:39Z\",\n  \"locations\": [],\n  \"organizations\": [],\n  \"template_combinations\": [],\n  \"puppetclasses\": []\n}"],"metadata":null,"see":[]},{"doc_url":"../../apidoc/v2/environments/update","name":"update","apis":[{"api_url":"/api/environments/:id","http_method":"PUT","short_description":"Update an environment","deprecated":null}],"formats":null,"full_description":"","errors":[],"params":[{"name":"id","full_name":"id","description":"","required":true,"allow_nil":false,"validator":"Must be an identifier, string from 1 to 128 characters containing only alphanumeric characters, space, underscore(_), hypen(-) with no leading or trailing space.","expected_type":"string","metadata":null,"show":true},{"name":"environment","full_name":"environment","description":"","required":true,"allow_nil":false,"validator":"Must be a Hash","expected_type":"hash","metadata":null,"show":true,"params":[{"name":"name","full_name":"environment[name]","description":"","required":false,"allow_nil":false,"validator":"Must be String","expected_type":"string","metadata":null,"show":true}]}],"examples":["PUT /api/environments/production\n{\n  \"environment\": {}\n}\n200\n{\n  \"created_at\": \"2014-09-02T14:00:17Z\",\n  \"hostgroups_count\": 0,\n  \"hosts_count\": 0,\n  \"id\": 334344675,\n  \"name\": \"production\",\n  \"updated_at\": \"2014-09-02T14:00:17Z\"\n}"],"metadata":null,"see":[]},{"doc_url":"../../apidoc/v2/environments/destroy","name":"destroy","apis":[{"api_url":"/api/environments/:id","http_method":"DELETE","short_description":"Delete an environment","deprecated":null}],"formats":null,"full_description":"","errors":[],"params":[{"name":"id","full_name":"id","description":"","required":true,"allow_nil":false,"validator":"Must be an identifier, string from 1 to 128 characters containing only alphanumeric characters, space, underscore(_), hypen(-) with no leading or trailing space.","expected_type":"string","metadata":null,"show":true}],"examples":["DELETE /api/environments/testing\n200\n{\n  \"created_at\": \"2014-09-02T14:00:17Z\",\n  \"hostgroups_count\": 0,\n  \"hosts_count\": 0,\n  \"id\": 687036937,\n  \"name\": \"testing\",\n  \"updated_at\": \"2014-09-02T14:00:17Z\"\n}"],"metadata":null,"see":[]}]}],"link_extension":".html"}}