{"docs":{"name":"Foreman","info":"\n\u003cp\u003eL\u0026#39;API v2 de Foreman est à présent l\u0026#39;API par défaut.\u003c/p\u003e\n","copyright":"","doc_url":"../../../apidoc/v2","api_url":"/api","resources":[{"doc_url":"../../../apidoc/v2/parameters","api_url":"/api","name":"Parameters","short_description":null,"full_description":"\n\u003cp\u003eThese API calls are related to \u003cstrong\u003enested parameters for a host,\ndomain, subnet, host group, operating system\u003c/strong\u003e. If you are looking\nfor \u0026lt;a href=“common_parameters.html”\u0026gt;global parameters\u0026lt;/a\u0026gt;, go\nto \u0026lt;a href=“common_parameters.html”\u0026gt;this link\u0026lt;/a\u0026gt;.\u003c/p\u003e\n","version":"v2","formats":null,"metadata":null,"methods":[{"doc_url":"../../../apidoc/v2/parameters/destroy","name":"destroy","apis":[{"api_url":"/api/hosts/:host_id/parameters/:id","http_method":"DELETE","short_description":"Supprimer une paramètre imbriqué pour un hôte","deprecated":null},{"api_url":"/api/hostgroups/:hostgroup_id/parameters/:id","http_method":"DELETE","short_description":"Supprimer un paramètre imbriqué pour un group d'hôtes","deprecated":null},{"api_url":"/api/domains/:domain_id/parameters/:id","http_method":"DELETE","short_description":"Supprimer un paramètre imbriqué pour un domaine","deprecated":null},{"api_url":"/api/operatingsystems/:operatingsystem_id/parameters/:id","http_method":"DELETE","short_description":"Supprimer une paramètre imbriqué pour un système d'exploitation","deprecated":null},{"api_url":"/api/locations/:location_id/parameters/:id","http_method":"DELETE","short_description":"Supprimer un paramètre imbriqué pour un emplacement","deprecated":null},{"api_url":"/api/organizations/:organization_id/parameters/:id","http_method":"DELETE","short_description":"Supprimer un paramètre imbriqué pour une organisation","deprecated":null},{"api_url":"/api/subnets/:subnet_id/parameters/:id","http_method":"DELETE","short_description":"Supprimer un paramètre imbriqué pour un sous-réseaux","deprecated":null}],"formats":null,"full_description":"","errors":[],"params":[{"name":"host_id","full_name":"host_id","description":"\n\u003cp\u003eID de l\u0026#39;hôte\u003c/p\u003e\n","required":false,"allow_nil":false,"allow_blank":false,"validator":"Must be a String","expected_type":"string","metadata":null,"show":true,"validations":[]},{"name":"hostgroup_id","full_name":"hostgroup_id","description":"\n\u003cp\u003eID du groupe d\u0026#39;hôtes\u003c/p\u003e\n","required":false,"allow_nil":false,"allow_blank":false,"validator":"Must be a String","expected_type":"string","metadata":null,"show":true,"validations":[]},{"name":"domain_id","full_name":"domain_id","description":"\n\u003cp\u003eID du domaine\u003c/p\u003e\n","required":false,"allow_nil":false,"allow_blank":false,"validator":"Must be a String","expected_type":"string","metadata":null,"show":true,"validations":[]},{"name":"operatingsystem_id","full_name":"operatingsystem_id","description":"\n\u003cp\u003eID du système d\u0026#39;exploitation\u003c/p\u003e\n","required":false,"allow_nil":false,"allow_blank":false,"validator":"Must be a String","expected_type":"string","metadata":null,"show":true,"validations":[]},{"name":"location_id","full_name":"location_id","description":"\n\u003cp\u003eID de l\u0026#39;emplacement\u003c/p\u003e\n","required":false,"allow_nil":false,"allow_blank":false,"validator":"Must be a String","expected_type":"string","metadata":null,"show":true,"validations":[]},{"name":"organization_id","full_name":"organization_id","description":"\n\u003cp\u003eID de l\u0026#39;organisation\u003c/p\u003e\n","required":false,"allow_nil":false,"allow_blank":false,"validator":"Must be a String","expected_type":"string","metadata":null,"show":true,"validations":[]},{"name":"id","full_name":"id","description":"\n\u003cp\u003eID du paramêtre\u003c/p\u003e\n","required":true,"allow_nil":false,"allow_blank":false,"validator":"Must be a String","expected_type":"string","metadata":null,"show":true,"validations":[]},{"name":"subnet_id","full_name":"subnet_id","description":"\n\u003cp\u003eID du sous-réseau\u003c/p\u003e\n","required":false,"allow_nil":false,"allow_blank":false,"validator":"Must be a String","expected_type":"string","metadata":null,"show":true,"validations":[]}],"examples":[],"metadata":null,"see":[],"headers":[],"show":true}],"headers":[],"deprecated":false}],"link_extension":".fr.html"}}