{"docs":{"name":"Foreman","info":"\n\u003cp\u003eForeman API v2 is currently the default API version.\u003c/p\u003e\n","copyright":"","doc_url":"../../../apidoc/v2","api_url":"/api","resources":[{"doc_url":"../../../apidoc/v2/puppetclasses","api_url":"/api","name":"Puppetclasses","short_description":null,"full_description":null,"version":"v2","formats":null,"metadata":null,"methods":[{"doc_url":"../../../apidoc/v2/puppetclasses/update","name":"update","apis":[{"api_url":"/api/puppetclasses/:id","http_method":"PUT","short_description":"Update a Puppet class","deprecated":null}],"formats":null,"full_description":"","errors":[],"params":[{"name":"id","full_name":"id","description":"","required":true,"allow_nil":false,"validator":"Must be String","expected_type":"string","metadata":null,"show":true,"validations":[]},{"name":"puppetclass","full_name":"puppetclass","description":"","required":true,"allow_nil":false,"validator":"Must be a Hash","expected_type":"hash","metadata":null,"show":true,"validations":[],"params":[{"name":"name","full_name":"puppetclass[name]","description":"","required":false,"allow_nil":false,"validator":"Must be String","expected_type":"string","metadata":null,"show":true,"validations":[]}]}],"examples":["PUT /api/puppetclasses/980190962-base\n{\n  \"puppetclass\": {\n    \"name\": \"test_puppetclass\"\n  }\n}\n200\n{\n  \"created_at\": \"2016-03-10 15:51:22 UTC\",\n  \"updated_at\": \"2016-03-10 15:52:32 UTC\",\n  \"id\": 980190962,\n  \"name\": \"test_puppetclass\",\n  \"module_name\": \"test_puppetclass\",\n  \"environments\": [\n    {\n      \"name\": \"production\",\n      \"id\": 334344675\n    }\n  ],\n  \"hostgroups\": [\n    {\n      \"id\": 636252244,\n      \"name\": \"Common\",\n      \"title\": \"Common\"\n    }\n  ],\n  \"smart_variables\": [\n    {\n      \"variable\": \"ssl_port\",\n      \"id\": 298486374\n    }\n  ],\n  \"smart_class_parameters\": [\n    {\n      \"parameter\": \"cluster\",\n      \"id\": 328495940\n    }\n  ]\n}"],"metadata":null,"see":[],"headers":[],"show":true}],"headers":null}],"link_extension":".it.html"}}